mdadiffusion/__init__.py
mdadiffusion/mda.py
mdadiffusion-0.0.1.dist-info/LICENSE
mdadiffusion-0.0.1.dist-info/METADATA
mdadiffusion-0.0.1.dist-info/WHEEL
mdadiffusion-0.0.1.dist-info/top_level.txt
mdadiffusion-0.0.1.dist-info/RECORD
