Metadata-Version: 2.1
Name: mdadiffusion
Version: 0.0.1
Summary: Minimum dissipation approximation for hydrodynamic size.
Home-page: https://github.com/RadostW/mdadiffusion/
Author: Radost Waszkiewicz
Author-email: radost.waszkiewicz@gmail.com
License: MIT
Project-URL: Source, https://github.com/RadostW/mdadiffusion/
License-File: LICENSE
Requires-Dist: numpy (>1.16)
Requires-Dist: pygrpy
Requires-Dist: sarw-spheres
